affectivecloud/__init__.py
affectivecloud/__version__.py
affectivecloud/client.py
affectivecloud/algorithm/__init__.py
affectivecloud/algorithm/affective_services.py
affectivecloud/algorithm/base_services.py
affectivecloud/protocols/__init__.py
affectivecloud/protocols/protocol.py
affectivecloud/protocols/requests/__init__.py
affectivecloud/protocols/requests/affective_service.py
affectivecloud/protocols/requests/base_service.py
affectivecloud/protocols/requests/session.py
affectivecloud/protocols/responses/__init__.py
affectivecloud/protocols/responses/affective_service.py
affectivecloud/protocols/responses/base.py
affectivecloud/protocols/responses/base_service.py
affectivecloud/protocols/responses/session.py
affectivecloud-1.1.0.dist-info/LICENSE
affectivecloud-1.1.0.dist-info/METADATA
affectivecloud-1.1.0.dist-info/WHEEL
affectivecloud-1.1.0.dist-info/dependency_links.txt
affectivecloud-1.1.0.dist-info/top_level.txt
affectivecloud-1.1.0.dist-info/RECORD
