Metadata-Version: 2.1
Name: affectivecloud
Version: 1.1.0
Summary: AffectiveCloud Python SDK
Home-page: https://github.com/Entertech/Enter-Affectivecloud-PC-SDK.git
Author: Lockey
Author-email: chenyitao@entertech.cn
License: Entertech
Platform: UNKNOWN
Classifier: Natural Language :: Chinese (Simplified)
Classifier: Development Status :: 4 - Beta
Classifier: Framework :: AsyncIO
Classifier: Intended Audience :: Developers
Classifier: Operating System :: Microsoft :: Windows :: Windows 10
Classifier: Operating System :: POSIX :: Linux
Classifier: Operating System :: MacOS :: MacOS X
Classifier: Programming Language :: Python
Classifier: Programming Language :: Python :: 3
Classifier: Programming Language :: Python :: 3.7
Classifier: Programming Language :: Python :: 3.8
Classifier: Programming Language :: Python :: 3.9
Classifier: Programming Language :: Python :: 3.10
Classifier: Programming Language :: Python :: Implementation :: CPython
License-File: LICENSE
Requires-Dist: websockets (==9.1)
